fudan_utils/__init__.py
fudan_utils/config.py
fudan_utils/fudan.py
fudan_utils/fudan_grades.py
fudan_utils/utils.py
fudan_utils-0.1.8.dist-info/METADATA
fudan_utils-0.1.8.dist-info/WHEEL
fudan_utils-0.1.8.dist-info/entry_points.txt
fudan_utils-0.1.8.dist-info/RECORD
