Metadata-Version: 2.1
Name: fudan-utils
Version: 0.1.8
Summary: Fudan UIS Login Utilities and More
Home-page: https://github.com/tddschn/fudan-utils
License: MIT
Keywords: Fudan University
Author: Teddy Xinyuan Chen
Author-email: 45612704+tddschn@users.noreply.github.com
Requires-Python: >=3.8,<4.0
Classifier: License :: OSI Approved :: MIT License
Classifier: Programming Language :: Python :: 3
Classifier: Programming Language :: Python :: 3.8
Classifier: Programming Language :: Python :: 3.9
Classifier: Programming Language :: Python :: 3.10
Classifier: Programming Language :: Python :: 3.11
Classifier: Topic :: Utilities
Requires-Dist: bs4[jwfw] (>=0.0.1,<0.0.2)
Requires-Dist: requests (>=2.31.0,<3.0.0)
Requires-Dist: tabulate[jwfw] (>=0.9.0,<0.10.0)
Requires-Dist: wcwidth[jwfw] (>=0.2.6,<0.3.0)
Project-URL: Bug Tracker, https://github.com/tddschn/fudan-utils/issues
Project-URL: Repository, https://github.com/tddschn/fudan-utils
